Metadata-Version: 2.1
Name: EZprofanity
Version: 0.0.5
Summary: Easily check for profane and innapropriate words quickly.
Author: Victor wolmarans
License-File: license.txt
